rriot/__init__.py
rriot/__main__.py
rriot/basic_api.py
rriot/constants.py
rriot/exceptions.py
rriot/hawk_api.py
rriot/rriot_data.py
python_rriot-0.0.4.dist-info/LICENSE
python_rriot-0.0.4.dist-info/METADATA
python_rriot-0.0.4.dist-info/WHEEL
python_rriot-0.0.4.dist-info/top_level.txt
python_rriot-0.0.4.dist-info/RECORD
